lipstick/__init__.py
lipstick/animations.py
lipstick/bar_plots.py
lipstick/scatter_plots.py
lipstick-0.0.7.dist-info/METADATA
lipstick-0.0.7.dist-info/WHEEL
lipstick-0.0.7.dist-info/top_level.txt
lipstick-0.0.7.dist-info/RECORD
