Metadata-Version: 2.1
Name: lipstick
Version: 0.0.7
Summary: A collection of plotting functions.
Home-page: https://github.com/mohammadbashiri/lipstick
Author: Mohammad Bashiri
Author-email: mohammadbashiri93@gmail.com
Requires-Dist: numpy
Requires-Dist: matplotlib (>=3.3.0)
Requires-Dist: pillow (>=7.2.0)
